.installed.cfg
.long-description.html
MANIFEST.in
README.rst
bootstrap.py
buildout.cfg
setup.py
collective/__init__.py
collective.recipe.grp.egg-info/PKG-INFO
collective.recipe.grp.egg-info/SOURCES.txt
collective.recipe.grp.egg-info/dependency_links.txt
collective.recipe.grp.egg-info/entry_points.txt
collective.recipe.grp.egg-info/namespace_packages.txt
collective.recipe.grp.egg-info/not-zip-safe
collective.recipe.grp.egg-info/requires.txt
collective.recipe.grp.egg-info/top_level.txt
collective/recipe/__init__.py
collective/recipe/grp/__init__.py
collective/recipe/grp/tests/__init__.py
collective/recipe/grp/tests/test_docs.py
docs/HISTORY.txt