Metadata-Version: 1.0
Name: collective.recipe.grp
Version: 1.1.0
Summary: A window unto Python's Standard Library grp function
Home-page: http://collective.github.com/collective.recipe.grp/
Author: Alex Clark
Author-email: aclark@aclark.net
License: ZPL
Keywords: buildout group id unix
Platform: UNKNOWN
Classifier: Framework :: Buildout
Classifier: Intended Audience :: Developers
Classifier: Topic :: Software Development :: Build Tools
Classifier: Topic :: Software Development :: Libraries :: Python Modules
Classifier: License :: OSI Approved :: Zope Public License
